[
  {"name":"Alexandr","averageGrade":4.82,"studentCardNumber":10037},
  {"name":"Sergey","averageGrade":3.91,"studentCardNumber":10012},
  {"name":"Artem","averageGrade":4.36,"studentCardNumber":10015},
  {"name":"Kirill","averageGrade":4.27,"studentCardNumber":10049},
  {"name":"Roman","averageGrade":3.76,"studentCardNumber":10004},
  {"name":"Anna","averageGrade":4.95,"studentCardNumber":10028},
  {"name":"Elena","averageGrade":4.11,"studentCardNumber":10045},
  {"name":"Dmitry","averageGrade":3.54,"studentCardNumber":10009},
  {"name":"Ivan","averageGrade":4.48,"studentCardNumber":10031},
  {"name":"Maria","averageGrade":4.73,"studentCardNumber":10018},
  {"name":"Olga","averageGrade":3.88,"studentCardNumber":10043},
  {"name":"Nikita","averageGrade":4.05,"studentCardNumber":10002},
  {"name":"Pavel","averageGrade":3.67,"studentCardNumber":10039},
  {"name":"Artem","averageGrade":4.36,"studentCardNumber":10015},
  {"name":"Denis","averageGrade":3.95,"studentCardNumber":10047},
  {"name":"Maksim","averageGrade":4.58,"studentCardNumber":10024},
  {"name":"Vladislav","averageGrade":4.14,"studentCardNumber":10006},
  {"name":"Andrey","averageGrade":3.72,"studentCardNumber":10033},
  {"name":"Yaroslav","averageGrade":4.67,"studentCardNumber":10020},
  {"name":"Timur","averageGrade":4.22,"studentCardNumber":10041},
  {"name":"Egor","averageGrade":3.81,"studentCardNumber":10014},
  {"name":"Viktor","averageGrade":4.44,"studentCardNumber":10050},
  {"name":"Oleg","averageGrade":3.63,"studentCardNumber":10027},
  {"name":"Ilya","averageGrade":4.31,"studentCardNumber":10008},
  {"name":"Stepan","averageGrade":4.09,"studentCardNumber":10035},
  {"name":"Gleb","averageGrade":3.58,"studentCardNumber":10017},
  {"name":"Matvey","averageGrade":4.79,"studentCardNumber":10029},
  {"name":"Vadim","averageGrade":4.18,"studentCardNumber":10011},
  {"name":"Konstantin","averageGrade":3.99,"studentCardNumber":10048},
  {"name":"Grigory","averageGrade":4.52,"studentCardNumber":10022},
  {"name":"Artem","averageGrade":4.36,"studentCardNumber":10015},
  {"name":"Arseniy","averageGrade":4.07,"studentCardNumber":10005},
  {"name":"Bogdan","averageGrade":3.84,"studentCardNumber":10044},
  {"name":"Ruslan","averageGrade":4.25,"studentCardNumber":10019},
  {"name":"Valeriy","averageGrade":3.69,"studentCardNumber":10030},
  {"name":"Gennady","averageGrade":4.41,"studentCardNumber":10007},
  {"name":"Fedor","averageGrade":4.13,"studentCardNumber":10038},
  {"name":"Leonid","averageGrade":3.77,"studentCardNumber":10001},
  {"name":"Vadislav","averageGrade":4.61,"studentCardNumber":10026},
  {"name":"Stanislav","averageGrade":4.02,"studentCardNumber":10013},
  {"name":"Valentin","averageGrade":3.56,"studentCardNumber":10046},
  {"name":"German","averageGrade":4.33,"studentCardNumber":10023},
  {"name":"Semyon","averageGrade":4.16,"studentCardNumber":10034},
  {"name":"Anatoliy","averageGrade":3.74,"studentCardNumber":10010},
  {"name":"Boris","averageGrade":4.57,"studentCardNumber":10042},
  {"name":"Yuriy","averageGrade":4.21,"studentCardNumber":10016},
  {"name":"Vitaliy","averageGrade":3.86,"studentCardNumber":10032},
  {"name":"Eduard","averageGrade":4.46,"studentCardNumber":10003},
  {"name":"Artem","averageGrade":4.36,"studentCardNumber":10015},
  {"name":"Aleksey","averageGrade":4.12,"studentCardNumber":10040},
  {"name":"Mikhail","averageGrade":3.97,"studentCardNumber":10021},
  {"name":"Georgiy","averageGrade":4.64,"studentCardNumber":10036},
  {"name":"Arkady","averageGrade":4.08,"studentCardNumber":10025},
  {"name":"Artem","averageGrade":4.36,"studentCardNumber":10015}
]
